ber_tlv/__init__.py
ber_tlv/tlv.py
ber_tlv-0.0.6.dist-info/LICENSE
ber_tlv-0.0.6.dist-info/METADATA
ber_tlv-0.0.6.dist-info/WHEEL
ber_tlv-0.0.6.dist-info/top_level.txt
ber_tlv-0.0.6.dist-info/RECORD
