Metadata-Version: 2.1
Name: ber-tlv
Version: 0.0.6
Summary: A EMV BER-TLV encoding/decoding package
Home-page: https://github.com/toumilov/python-ber-tlv
Author: Andrey Toumilovich
Author-email: andrey.toumilovich@gmail.com
License: UNKNOWN
Project-URL: Bug Tracker, https://github.com/toumilov/python-ber-tlv/issues
Platform: UNKNOWN
Classifier: Programming Language :: Python :: 3
Classifier: License :: OSI Approved :: MIT License
Classifier: Operating System :: OS Independent
Requires-Python: >=3.4
License-File: LICENSE
